certbot_dns_dynudns/__init__.py
certbot_dns_dynudns/dns_dynu.py
certbot_dns_dynudns/dns_dynu_test.py
certbot_dns_dynudns-0.0.6.dist-info/LICENSE
certbot_dns_dynudns-0.0.6.dist-info/METADATA
certbot_dns_dynudns-0.0.6.dist-info/WHEEL
certbot_dns_dynudns-0.0.6.dist-info/entry_points.txt
certbot_dns_dynudns-0.0.6.dist-info/top_level.txt
certbot_dns_dynudns-0.0.6.dist-info/RECORD
