Metadata-Version: 2.1
Name: certbot-dns-dynudns
Version: 0.0.6
Summary: Dynu DNS Authenticator plugin for Certbot
Home-page: https://github.com/DustyRah/certbot-dns-dynudns
Download-URL: https://github.com/DustyRah/certbot-dns-dynudns/archive/refs/tags/0.0.6.tar.gz
Author: DustyRah
License: Apache License 2.0
Classifier: Development Status :: 5 - Production/Stable
Classifier: Environment :: Plugins
Classifier: Intended Audience :: System Administrators
Classifier: License :: OSI Approved :: Apache Software License
Classifier: Operating System :: POSIX :: Linux
Classifier: Programming Language :: Python
Classifier: Programming Language :: Python :: 2
Classifier: Programming Language :: Python :: 2.7
Classifier: Programming Language :: Python :: 3
Classifier: Programming Language :: Python :: 3.5
Classifier: Programming Language :: Python :: 3.6
Classifier: Programming Language :: Python :: 3.7
Classifier: Programming Language :: Python :: 3.8
Classifier: Programming Language :: Python :: 3.9
Classifier: Programming Language :: Python :: 3.10
Classifier: Programming Language :: Python :: 3.11
Classifier: Topic :: Internet :: WWW/HTTP
Classifier: Topic :: Security
Classifier: Topic :: System :: Installation/Setup
Classifier: Topic :: System :: Networking
Classifier: Topic :: System :: Systems Administration
Classifier: Topic :: Utilities
Requires-Python: >=2.7, !=3.0.*, !=3.1.*, !=3.2.*, !=3.3.*
License-File: LICENSE
Requires-Dist: acme >=2.0.0
Requires-Dist: certbot >=2.0.0
Requires-Dist: dns-lexicon >=3.11.7
Requires-Dist: dnspython
Requires-Dist: mock
Requires-Dist: setuptools
Requires-Dist: requests
